{
  "19375": [
    {
      "datetime": "2023-03-31T17:06:38",
      "cpu": 0.0,
      "rss": 78032
    },
    {
      "datetime": "2023-03-31T17:06:45",
      "cpu": 0.8,
      "rss": 79008
    },
    {
      "datetime": "2023-03-31T17:06:46",
      "cpu": 0.1,
      "rss": 79008
    },
    {
      "datetime": "2023-03-31T17:06:47",
      "cpu": 0.2,
      "rss": 79008
    },
    {
      "datetime": "2023-03-31T17:06:48",
      "cpu": 0.1,
      "rss": 79024
    },
    {
      "datetime": "2023-03-31T17:06:49",
      "cpu": 0.0,
      "rss": 79024
    },
    {
      "datetime": "2023-03-31T17:06:50",
      "cpu": 0.3,
      "rss": 79040
    },
    {
      "datetime": "2023-03-31T17:06:52",
      "cpu": 0.0,
      "rss": 79040
    },
    {
      "datetime": "2023-03-31T17:06:53",
      "cpu": 0.3,
      "rss": 79040
    },
    {
      "datetime": "2023-03-31T17:06:54",
      "cpu": 0.0,
      "rss": 79040
    },
    {
      "datetime": "2023-03-31T17:06:57",
      "cpu": 0.1,
      "rss": 79040
    },
    {
      "datetime": "2023-03-31T17:06:58",
      "cpu": 0.0,
      "rss": 79040
    },
    {
      "datetime": "2023-03-31T17:07:00",
      "cpu": 0.9,
      "rss": 79056
    },
    {
      "datetime": "2023-03-31T17:07:01",
      "cpu": 0.3,
      "rss": 79056
    },
    {
      "datetime": "2023-03-31T17:07:02",
      "cpu": 0.2,
      "rss": 79072
    },
    {
      "datetime": "2023-03-31T17:07:03",
      "cpu": 0.0,
      "rss": 79072
    },
    {
      "datetime": "2023-03-31T17:07:04",
      "cpu": 0.3,
      "rss": 79072
    },
    {
      "datetime": "2023-03-31T17:07:06",
      "cpu": 0.0,
      "rss": 79072
    },
    {
      "datetime": "2023-03-31T17:07:07",
      "cpu": 0.2,
      "rss": 79072
    },
    {
      "datetime": "2023-03-31T17:07:08",
      "cpu": 0.0,
      "rss": 79072
    },
    {
      "datetime": "2023-03-31T17:07:09",
      "cpu": 0.1,
      "rss": 79072
    },
    {
      "datetime": "2023-03-31T17:07:10",
      "cpu": 0.0,
      "rss": 79072
    },
    {
      "datetime": "2023-03-31T17:07:14",
      "cpu": 0.7,
      "rss": 79072
    },
    {
      "datetime": "2023-03-31T17:07:15",
      "cpu": 0.0,
      "rss": 79072
    },
    {
      "datetime": "2023-03-31T17:07:16",
      "cpu": 0.4,
      "rss": 79072
    },
    {
      "datetime": "2023-03-31T17:07:17",
      "cpu": 0.0,
      "rss": 79072
    },
    {
      "datetime": "2023-03-31T17:07:18",
      "cpu": 0.2,
      "rss": 79072
    },
    {
      "datetime": "2023-03-31T17:07:20",
      "cpu": 0.0,
      "rss": 79072
    },
    {
      "datetime": "2023-03-31T17:07:21",
      "cpu": 0.3,
      "rss": 79072
    },
    {
      "datetime": "2023-03-31T17:07:22",
      "cpu": 0.0,
      "rss": 79072
    },
    {
      "datetime": "2023-03-31T17:07:23",
      "cpu": 0.1,
      "rss": 79072
    },
    {
      "datetime": "2023-03-31T17:07:24",
      "cpu": 0.0,
      "rss": 79072
    },
    {
      "datetime": "2023-03-31T17:07:28",
      "cpu": 0.0,
      "rss": 79088
    },
    {
      "datetime": "2023-03-31T17:07:29",
      "cpu": 0.2,
      "rss": 79088
    },
    {
      "datetime": "2023-03-31T17:07:30",
      "cpu": 0.4,
      "rss": 79088
    },
    {
      "datetime": "2023-03-31T17:07:31",
      "cpu": 0.0,
      "rss": 79088
    },
    {
      "datetime": "2023-03-31T17:07:32",
      "cpu": 0.3,
      "rss": 79088
    },
    {
      "datetime": "2023-03-31T17:07:34",
      "cpu": 0.0,
      "rss": 79088
    },
    {
      "datetime": "2023-03-31T17:07:35",
      "cpu": 0.4,
      "rss": 79088
    },
    {
      "datetime": "2023-03-31T17:07:36",
      "cpu": 0.0,
      "rss": 79088
    },
    {
      "datetime": "2023-03-31T17:07:37",
      "cpu": 0.2,
      "rss": 79088
    },
    {
      "datetime": "2023-03-31T17:07:38",
      "cpu": 0.0,
      "rss": 79088
    },
    {
      "datetime": "2023-03-31T17:07:42",
      "cpu": 0.7,
      "rss": 79120
    },
    {
      "datetime": "2023-03-31T17:07:43",
      "cpu": 0.3,
      "rss": 79120
    },
    {
      "datetime": "2023-03-31T17:07:44",
      "cpu": 0.4,
      "rss": 79120
    },
    {
      "datetime": "2023-03-31T17:07:45",
      "cpu": 0.0,
      "rss": 79120
    },
    {
      "datetime": "2023-03-31T17:07:47",
      "cpu": 0.3,
      "rss": 79120
    },
    {
      "datetime": "2023-03-31T17:07:48",
      "cpu": 0.0,
      "rss": 79120
    },
    {
      "datetime": "2023-03-31T17:07:49",
      "cpu": 0.4,
      "rss": 79120
    },
    {
      "datetime": "2023-03-31T17:07:50",
      "cpu": 0.0,
      "rss": 79120
    },
    {
      "datetime": "2023-03-31T17:07:51",
      "cpu": 0.1,
      "rss": 79120
    },
    {
      "datetime": "2023-03-31T17:07:52",
      "cpu": 0.0,
      "rss": 79120
    },
    {
      "datetime": "2023-03-31T17:07:57",
      "cpu": 0.3,
      "rss": 79120
    },
    {
      "datetime": "2023-03-31T17:07:58",
      "cpu": 0.9,
      "rss": 79120
    },
    {
      "datetime": "2023-03-31T17:07:59",
      "cpu": 0.0,
      "rss": 79120
    },
    {
      "datetime": "2023-03-31T17:08:01",
      "cpu": 0.3,
      "rss": 79120
    },
    {
      "datetime": "2023-03-31T17:08:02",
      "cpu": 0.0,
      "rss": 79120
    },
    {
      "datetime": "2023-03-31T17:08:03",
      "cpu": 0.4,
      "rss": 79120
    },
    {
      "datetime": "2023-03-31T17:08:04",
      "cpu": 0.0,
      "rss": 79120
    },
    {
      "datetime": "2023-03-31T17:08:05",
      "cpu": 0.1,
      "rss": 79120
    },
    {
      "datetime": "2023-03-31T17:08:06",
      "cpu": 0.0,
      "rss": 79120
    },
    {
      "datetime": "2023-03-31T17:08:09",
      "cpu": 0.0,
      "rss": 79136
    },
    {
      "datetime": "2023-03-31T17:08:10",
      "cpu": 1.0,
      "rss": 79136
    },
    {
      "datetime": "2023-03-31T17:08:11",
      "cpu": 0.2,
      "rss": 79136
    },
    {
      "datetime": "2023-03-31T17:08:12",
      "cpu": 0.4,
      "rss": 79136
    },
    {
      "datetime": "2023-03-31T17:08:13",
      "cpu": 0.1,
      "rss": 79136
    },
    {
      "datetime": "2023-03-31T17:08:15",
      "cpu": 0.2,
      "rss": 79136
    },
    {
      "datetime": "2023-03-31T17:08:16",
      "cpu": 0.0,
      "rss": 79136
    },
    {
      "datetime": "2023-03-31T17:08:17",
      "cpu": 0.1,
      "rss": 79136
    },
    {
      "datetime": "2023-03-31T17:08:18",
      "cpu": 0.0,
      "rss": 79136
    },
    {
      "datetime": "2023-03-31T17:08:19",
      "cpu": 0.2,
      "rss": 79136
    },
    {
      "datetime": "2023-03-31T17:08:20",
      "cpu": 0.0,
      "rss": 79136
    },
    {
      "datetime": "2023-03-31T17:08:24",
      "cpu": 0.6,
      "rss": 79136
    },
    {
      "datetime": "2023-03-31T17:08:25",
      "cpu": 0.3,
      "rss": 79136
    },
    {
      "datetime": "2023-03-31T17:08:28",
      "cpu": 0.1,
      "rss": 79136
    },
    {
      "datetime": "2023-03-31T17:08:29",
      "cpu": 0.2,
      "rss": 79136
    },
    {
      "datetime": "2023-03-31T17:08:30",
      "cpu": 0.0,
      "rss": 79136
    },
    {
      "datetime": "2023-03-31T17:08:31",
      "cpu": 0.3,
      "rss": 79136
    },
    {
      "datetime": "2023-03-31T17:08:32",
      "cpu": 0.0,
      "rss": 79136
    },
    {
      "datetime": "2023-03-31T17:08:33",
      "cpu": 0.1,
      "rss": 79152
    },
    {
      "datetime": "2023-03-31T17:08:34",
      "cpu": 0.0,
      "rss": 79152
    },
    {
      "datetime": "2023-03-31T17:08:35",
      "cpu": 0.1,
      "rss": 79152
    },
    {
      "datetime": "2023-03-31T17:08:36",
      "cpu": 0.0,
      "rss": 79152
    },
    {
      "datetime": "2023-03-31T17:08:38",
      "cpu": 0.2,
      "rss": 79152
    },
    {
      "datetime": "2023-03-31T17:08:40",
      "cpu": 0.1,
      "rss": 79152
    },
    {
      "datetime": "2023-03-31T17:08:43",
      "cpu": 0.0,
      "rss": 79152
    },
    {
      "datetime": "2023-03-31T17:08:45",
      "cpu": 0.3,
      "rss": 79152
    },
    {
      "datetime": "2023-03-31T17:08:46",
      "cpu": 0.0,
      "rss": 79152
    },
    {
      "datetime": "2023-03-31T17:08:47",
      "cpu": 0.1,
      "rss": 79152
    },
    {
      "datetime": "2023-03-31T17:08:48",
      "cpu": 0.0,
      "rss": 79168
    },
    {
      "datetime": "2023-03-31T17:08:52",
      "cpu": 0.7,
      "rss": 79168
    },
    {
      "datetime": "2023-03-31T17:08:53",
      "cpu": 0.1,
      "rss": 79168
    },
    {
      "datetime": "2023-03-31T17:08:55",
      "cpu": 0.3,
      "rss": 79168
    },
    {
      "datetime": "2023-03-31T17:08:56",
      "cpu": 0.0,
      "rss": 79168
    },
    {
      "datetime": "2023-03-31T17:08:57",
      "cpu": 0.5,
      "rss": 79168
    },
    {
      "datetime": "2023-03-31T17:08:58",
      "cpu": 0.0,
      "rss": 79168
    },
    {
      "datetime": "2023-03-31T17:08:59",
      "cpu": 0.3,
      "rss": 79168
    },
    {
      "datetime": "2023-03-31T17:09:00",
      "cpu": 0.0,
      "rss": 79168
    },
    {
      "datetime": "2023-03-31T17:09:01",
      "cpu": 0.2,
      "rss": 79168
    },
    {
      "datetime": "2023-03-31T17:09:02",
      "cpu": 0.0,
      "rss": 79168
    },
    {
      "datetime": "2023-03-31T17:09:06",
      "cpu": 0.6,
      "rss": 79168
    },
    {
      "datetime": "2023-03-31T17:09:07",
      "cpu": 0.2,
      "rss": 79168
    },
    {
      "datetime": "2023-03-31T17:09:08",
      "cpu": 0.3,
      "rss": 79168
    },
    {
      "datetime": "2023-03-31T17:09:10",
      "cpu": 0.2,
      "rss": 79168
    },
    {
      "datetime": "2023-03-31T17:09:11",
      "cpu": 0.4,
      "rss": 79168
    },
    {
      "datetime": "2023-03-31T17:09:12",
      "cpu": 0.0,
      "rss": 79168
    },
    {
      "datetime": "2023-03-31T17:09:13",
      "cpu": 0.2,
      "rss": 79168
    },
    {
      "datetime": "2023-03-31T17:09:14",
      "cpu": 0.0,
      "rss": 79168
    },
    {
      "datetime": "2023-03-31T17:09:15",
      "cpu": 0.1,
      "rss": 79168
    },
    {
      "datetime": "2023-03-31T17:09:16",
      "cpu": 0.0,
      "rss": 79168
    },
    {
      "datetime": "2023-03-31T17:09:20",
      "cpu": 0.6,
      "rss": 79168
    },
    {
      "datetime": "2023-03-31T17:09:21",
      "cpu": 0.2,
      "rss": 79168
    },
    {
      "datetime": "2023-03-31T17:09:23",
      "cpu": 0.3,
      "rss": 79168
    },
    {
      "datetime": "2023-03-31T17:09:24",
      "cpu": 0.0,
      "rss": 79168
    },
    {
      "datetime": "2023-03-31T17:09:25",
      "cpu": 0.4,
      "rss": 79168
    },
    {
      "datetime": "2023-03-31T17:09:26",
      "cpu": 0.0,
      "rss": 79168
    },
    {
      "datetime": "2023-03-31T17:09:27",
      "cpu": 0.4,
      "rss": 79168
    },
    {
      "datetime": "2023-03-31T17:09:28",
      "cpu": 0.0,
      "rss": 79168
    },
    {
      "datetime": "2023-03-31T17:09:34",
      "cpu": 0.6,
      "rss": 79168
    },
    {
      "datetime": "2023-03-31T17:09:35",
      "cpu": 0.1,
      "rss": 79168
    },
    {
      "datetime": "2023-03-31T17:09:37",
      "cpu": 0.4,
      "rss": 79168
    },
    {
      "datetime": "2023-03-31T17:09:38",
      "cpu": 0.1,
      "rss": 79168
    },
    {
      "datetime": "2023-03-31T17:09:39",
      "cpu": 0.3,
      "rss": 79168
    },
    {
      "datetime": "2023-03-31T17:09:40",
      "cpu": 0.1,
      "rss": 79168
    },
    {
      "datetime": "2023-03-31T17:09:41",
      "cpu": 0.3,
      "rss": 79168
    },
    {
      "datetime": "2023-03-31T17:09:42",
      "cpu": 0.0,
      "rss": 79168
    },
    {
      "datetime": "2023-03-31T17:09:43",
      "cpu": 0.1,
      "rss": 79168
    },
    {
      "datetime": "2023-03-31T17:09:44",
      "cpu": 0.0,
      "rss": 79168
    },
    {
      "datetime": "2023-03-31T17:09:45",
      "cpu": 0.4,
      "rss": 79200
    },
    {
      "datetime": "2023-03-31T17:09:46",
      "cpu": 0.0,
      "rss": 79200
    },
    {
      "datetime": "2023-03-31T17:09:48",
      "cpu": 0.7,
      "rss": 79200
    },
    {
      "datetime": "2023-03-31T17:09:50",
      "cpu": 0.4,
      "rss": 79200
    },
    {
      "datetime": "2023-03-31T17:09:51",
      "cpu": 0.3,
      "rss": 79200
    },
    {
      "datetime": "2023-03-31T17:09:52",
      "cpu": 3.4,
      "rss": 79296
    },
    {
      "datetime": "2023-03-31T17:09:53",
      "cpu": 0.3,
      "rss": 79296
    },
    {
      "datetime": "2023-03-31T17:09:54",
      "cpu": 0.0,
      "rss": 79296
    },
    {
      "datetime": "2023-03-31T17:09:55",
      "cpu": 1.5,
      "rss": 79456
    },
    {
      "datetime": "2023-03-31T17:09:56",
      "cpu": 0.9,
      "rss": 79632
    },
    {
      "datetime": "2023-03-31T17:09:57",
      "cpu": 1.0,
      "rss": 79776
    },
    {
      "datetime": "2023-03-31T17:09:58",
      "cpu": 0.5,
      "rss": 79824
    },
    {
      "datetime": "2023-03-31T17:09:59",
      "cpu": 0.0,
      "rss": 79824
    },
    {
      "datetime": "2023-03-31T17:10:01",
      "cpu": 0.1,
      "rss": 79952
    },
    {
      "datetime": "2023-03-31T17:10:02",
      "cpu": 0.6,
      "rss": 79952
    },
    {
      "datetime": "2023-03-31T17:10:03",
      "cpu": 0.2,
      "rss": 79952
    },
    {
      "datetime": "2023-03-31T17:10:05",
      "cpu": 0.1,
      "rss": 79952
    },
    {
      "datetime": "2023-03-31T17:10:06",
      "cpu": 9.0,
      "rss": 80416
    },
    {
      "datetime": "2023-03-31T17:10:07",
      "cpu": 0.5,
      "rss": 80432
    },
    {
      "datetime": "2023-03-31T17:10:08",
      "cpu": 0.2,
      "rss": 80432
    },
    {
      "datetime": "2023-03-31T17:10:09",
      "cpu": 0.1,
      "rss": 80432
    },
    {
      "datetime": "2023-03-31T17:10:10",
      "cpu": 0.0,
      "rss": 80432
    },
    {
      "datetime": "2023-03-31T17:10:11",
      "cpu": 2.5,
      "rss": 80832
    },
    {
      "datetime": "2023-03-31T17:10:12",
      "cpu": 0.0,
      "rss": 80832
    },
    {
      "datetime": "2023-03-31T17:10:19",
      "cpu": 0.8,
      "rss": 80832
    },
    {
      "datetime": "2023-03-31T17:10:20",
      "cpu": 0.2,
      "rss": 80832
    },
    {
      "datetime": "2023-03-31T17:10:21",
      "cpu": 0.6,
      "rss": 80848
    },
    {
      "datetime": "2023-03-31T17:10:22",
      "cpu": 0.1,
      "rss": 80848
    },
    {
      "datetime": "2023-03-31T17:10:23",
      "cpu": 0.3,
      "rss": 80848
    },
    {
      "datetime": "2023-03-31T17:10:24",
      "cpu": 0.1,
      "rss": 80848
    },
    {
      "datetime": "2023-03-31T17:10:26",
      "cpu": 0.0,
      "rss": 80848
    },
    {
      "datetime": "2023-03-31T17:10:30",
      "cpu": 0.6,
      "rss": 80848
    },
    {
      "datetime": "2023-03-31T17:10:31",
      "cpu": 0.0,
      "rss": 80848
    },
    {
      "datetime": "2023-03-31T17:10:33",
      "cpu": 0.7,
      "rss": 80848
    },
    {
      "datetime": "2023-03-31T17:10:34",
      "cpu": 0.1,
      "rss": 80848
    },
    {
      "datetime": "2023-03-31T17:10:35",
      "cpu": 0.5,
      "rss": 80848
    },
    {
      "datetime": "2023-03-31T17:10:36",
      "cpu": 0.0,
      "rss": 80848
    },
    {
      "datetime": "2023-03-31T17:10:37",
      "cpu": 0.4,
      "rss": 80848
    },
    {
      "datetime": "2023-03-31T17:10:38",
      "cpu": 0.0,
      "rss": 80848
    },
    {
      "datetime": "2023-03-31T17:10:39",
      "cpu": 0.1,
      "rss": 80848
    },
    {
      "datetime": "2023-03-31T17:10:40",
      "cpu": 0.0,
      "rss": 80848
    },
    {
      "datetime": "2023-03-31T17:10:44",
      "cpu": 0.6,
      "rss": 80848
    },
    {
      "datetime": "2023-03-31T17:10:45",
      "cpu": 0.0,
      "rss": 80848
    },
    {
      "datetime": "2023-03-31T17:10:47",
      "cpu": 0.7,
      "rss": 80848
    },
    {
      "datetime": "2023-03-31T17:10:48",
      "cpu": 0.2,
      "rss": 80848
    },
    {
      "datetime": "2023-03-31T17:10:49",
      "cpu": 1.2,
      "rss": 80768
    },
    {
      "datetime": "2023-03-31T17:10:50",
      "cpu": 0.1,
      "rss": 80768
    },
    {
      "datetime": "2023-03-31T17:10:51",
      "cpu": 0.0,
      "rss": 80768
    },
    {
      "datetime": "2023-03-31T17:10:53",
      "cpu": 0.1,
      "rss": 80768
    },
    {
      "datetime": "2023-03-31T17:10:54",
      "cpu": 0.0,
      "rss": 80768
    },
    {
      "datetime": "2023-03-31T17:10:59",
      "cpu": 0.0,
      "rss": 59328
    },
    {
      "datetime": "2023-03-31T17:11:01",
      "cpu": 0.2,
      "rss": 59328
    },
    {
      "datetime": "2023-03-31T17:11:02",
      "cpu": 0.0,
      "rss": 59328
    },
    {
      "datetime": "2023-03-31T17:11:03",
      "cpu": 10.9,
      "rss": 76688
    }
  ]
}