{
  "77464": [
    {
      "datetime": "2023-03-31T13:59:16",
      "cpu": 0.0,
      "rss": 70736
    },
    {
      "datetime": "2023-03-31T13:59:21",
      "cpu": 0.0,
      "rss": 70784
    },
    {
      "datetime": "2023-03-31T13:59:22",
      "cpu": 0.0,
      "rss": 70800
    },
    {
      "datetime": "2023-03-31T13:59:25",
      "cpu": 0.1,
      "rss": 70800
    },
    {
      "datetime": "2023-03-31T13:59:26",
      "cpu": 0.0,
      "rss": 70800
    },
    {
      "datetime": "2023-03-31T13:59:27",
      "cpu": 0.3,
      "rss": 70800
    },
    {
      "datetime": "2023-03-31T13:59:29",
      "cpu": 0.0,
      "rss": 70800
    },
    {
      "datetime": "2023-03-31T13:59:30",
      "cpu": 0.1,
      "rss": 70800
    },
    {
      "datetime": "2023-03-31T13:59:31",
      "cpu": 0.0,
      "rss": 70800
    },
    {
      "datetime": "2023-03-31T13:59:38",
      "cpu": 0.0,
      "rss": 61392
    },
    {
      "datetime": "2023-03-31T13:59:39",
      "cpu": 0.1,
      "rss": 60752
    },
    {
      "datetime": "2023-03-31T13:59:40",
      "cpu": 0.0,
      "rss": 60672
    },
    {
      "datetime": "2023-03-31T13:59:44",
      "cpu": 0.1,
      "rss": 60672
    },
    {
      "datetime": "2023-03-31T13:59:45",
      "cpu": 0.0,
      "rss": 60672
    },
    {
      "datetime": "2023-03-31T13:59:49",
      "cpu": 0.0,
      "rss": 60704
    },
    {
      "datetime": "2023-03-31T13:59:53",
      "cpu": 0.5,
      "rss": 60704
    },
    {
      "datetime": "2023-03-31T13:59:54",
      "cpu": 0.0,
      "rss": 60704
    },
    {
      "datetime": "2023-03-31T13:59:56",
      "cpu": 0.1,
      "rss": 60704
    },
    {
      "datetime": "2023-03-31T13:59:57",
      "cpu": 0.0,
      "rss": 60704
    },
    {
      "datetime": "2023-03-31T14:00:05",
      "cpu": 0.3,
      "rss": 60704
    },
    {
      "datetime": "2023-03-31T14:00:06",
      "cpu": 0.0,
      "rss": 60704
    },
    {
      "datetime": "2023-03-31T14:00:07",
      "cpu": 0.2,
      "rss": 60704
    },
    {
      "datetime": "2023-03-31T14:00:09",
      "cpu": 0.0,
      "rss": 60704
    },
    {
      "datetime": "2023-03-31T14:00:18",
      "cpu": 0.1,
      "rss": 60784
    },
    {
      "datetime": "2023-03-31T14:00:19",
      "cpu": 0.0,
      "rss": 60784
    },
    {
      "datetime": "2023-03-31T14:00:29",
      "cpu": 0.0,
      "rss": 60864
    },
    {
      "datetime": "2023-03-31T14:00:33",
      "cpu": 0.3,
      "rss": 60864
    },
    {
      "datetime": "2023-03-31T14:00:34",
      "cpu": 0.0,
      "rss": 60864
    },
    {
      "datetime": "2023-03-31T14:00:38",
      "cpu": 0.1,
      "rss": 60864
    },
    {
      "datetime": "2023-03-31T14:00:39",
      "cpu": 0.0,
      "rss": 60864
    },
    {
      "datetime": "2023-03-31T14:00:43",
      "cpu": 0.0,
      "rss": 60880
    },
    {
      "datetime": "2023-03-31T14:00:45",
      "cpu": 0.1,
      "rss": 60880
    },
    {
      "datetime": "2023-03-31T14:00:47",
      "cpu": 0.0,
      "rss": 60880
    },
    {
      "datetime": "2023-03-31T14:00:54",
      "cpu": 0.0,
      "rss": 60848
    },
    {
      "datetime": "2023-03-31T14:00:57",
      "cpu": 0.0,
      "rss": 60496
    },
    {
      "datetime": "2023-03-31T14:00:58",
      "cpu": 0.0,
      "rss": 60528
    },
    {
      "datetime": "2023-03-31T14:00:59",
      "cpu": 0.2,
      "rss": 60528
    },
    {
      "datetime": "2023-03-31T14:01:01",
      "cpu": 0.0,
      "rss": 60528
    },
    {
      "datetime": "2023-03-31T14:01:02",
      "cpu": 0.1,
      "rss": 60528
    },
    {
      "datetime": "2023-03-31T14:01:03",
      "cpu": 0.0,
      "rss": 60528
    },
    {
      "datetime": "2023-03-31T14:01:11",
      "cpu": 0.3,
      "rss": 60528
    },
    {
      "datetime": "2023-03-31T14:01:13",
      "cpu": 0.0,
      "rss": 60528
    },
    {
      "datetime": "2023-03-31T14:01:14",
      "cpu": 0.2,
      "rss": 60528
    },
    {
      "datetime": "2023-03-31T14:01:15",
      "cpu": 0.0,
      "rss": 60528
    },
    {
      "datetime": "2023-03-31T14:01:23",
      "cpu": 0.1,
      "rss": 60528
    },
    {
      "datetime": "2023-03-31T14:01:25",
      "cpu": 0.0,
      "rss": 60528
    },
    {
      "datetime": "2023-03-31T14:01:26",
      "cpu": 0.1,
      "rss": 60528
    },
    {
      "datetime": "2023-03-31T14:01:27",
      "cpu": 0.0,
      "rss": 60528
    },
    {
      "datetime": "2023-03-31T14:01:28",
      "cpu": 0.1,
      "rss": 60528
    },
    {
      "datetime": "2023-03-31T14:01:29",
      "cpu": 0.0,
      "rss": 60528
    },
    {
      "datetime": "2023-03-31T14:01:38",
      "cpu": 0.3,
      "rss": 60528
    },
    {
      "datetime": "2023-03-31T14:01:39",
      "cpu": 0.0,
      "rss": 60528
    },
    {
      "datetime": "2023-03-31T14:01:40",
      "cpu": 0.1,
      "rss": 60528
    },
    {
      "datetime": "2023-03-31T14:01:41",
      "cpu": 0.0,
      "rss": 60528
    },
    {
      "datetime": "2023-03-31T14:01:52",
      "cpu": 0.2,
      "rss": 60528
    },
    {
      "datetime": "2023-03-31T14:01:53",
      "cpu": 0.0,
      "rss": 60528
    },
    {
      "datetime": "2023-03-31T14:01:54",
      "cpu": 0.1,
      "rss": 60528
    },
    {
      "datetime": "2023-03-31T14:01:55",
      "cpu": 0.0,
      "rss": 60528
    },
    {
      "datetime": "2023-03-31T14:02:03",
      "cpu": 0.1,
      "rss": 60528
    },
    {
      "datetime": "2023-03-31T14:02:04",
      "cpu": 0.0,
      "rss": 60528
    },
    {
      "datetime": "2023-03-31T14:02:06",
      "cpu": 0.3,
      "rss": 60528
    },
    {
      "datetime": "2023-03-31T14:02:07",
      "cpu": 0.0,
      "rss": 60528
    },
    {
      "datetime": "2023-03-31T14:02:10",
      "cpu": 0.1,
      "rss": 60528
    },
    {
      "datetime": "2023-03-31T14:02:11",
      "cpu": 0.0,
      "rss": 60528
    },
    {
      "datetime": "2023-03-31T14:02:22",
      "cpu": 0.3,
      "rss": 60528
    },
    {
      "datetime": "2023-03-31T14:02:23",
      "cpu": 0.0,
      "rss": 60528
    },
    {
      "datetime": "2023-03-31T14:02:24",
      "cpu": 0.1,
      "rss": 60528
    },
    {
      "datetime": "2023-03-31T14:02:25",
      "cpu": 0.0,
      "rss": 60528
    },
    {
      "datetime": "2023-03-31T14:02:26",
      "cpu": 0.1,
      "rss": 60528
    },
    {
      "datetime": "2023-03-31T14:02:27",
      "cpu": 0.0,
      "rss": 61088
    },
    {
      "datetime": "2023-03-31T14:02:34",
      "cpu": 0.3,
      "rss": 61056
    },
    {
      "datetime": "2023-03-31T14:02:35",
      "cpu": 0.0,
      "rss": 61056
    },
    {
      "datetime": "2023-03-31T14:02:38",
      "cpu": 0.1,
      "rss": 61056
    },
    {
      "datetime": "2023-03-31T14:02:39",
      "cpu": 0.0,
      "rss": 61056
    },
    {
      "datetime": "2023-03-31T14:02:43",
      "cpu": 0.0,
      "rss": 61088
    },
    {
      "datetime": "2023-03-31T14:02:48",
      "cpu": 0.3,
      "rss": 61088
    },
    {
      "datetime": "2023-03-31T14:02:49",
      "cpu": 0.0,
      "rss": 61088
    },
    {
      "datetime": "2023-03-31T14:02:50",
      "cpu": 0.1,
      "rss": 61088
    },
    {
      "datetime": "2023-03-31T14:02:51",
      "cpu": 0.0,
      "rss": 56176
    },
    {
      "datetime": "2023-03-31T14:02:52",
      "cpu": 0.0,
      "rss": 54464
    },
    {
      "datetime": "2023-03-31T14:02:55",
      "cpu": 0.0,
      "rss": 39072
    },
    {
      "datetime": "2023-03-31T14:02:56",
      "cpu": 0.0,
      "rss": 29072
    },
    {
      "datetime": "2023-03-31T14:02:58",
      "cpu": 0.0,
      "rss": 29088
    },
    {
      "datetime": "2023-03-31T14:03:02",
      "cpu": 0.1,
      "rss": 29088
    },
    {
      "datetime": "2023-03-31T14:03:03",
      "cpu": 0.0,
      "rss": 29088
    },
    {
      "datetime": "2023-03-31T14:03:15",
      "cpu": 0.0,
      "rss": 29008
    },
    {
      "datetime": "2023-03-31T14:03:16",
      "cpu": 0.2,
      "rss": 29008
    },
    {
      "datetime": "2023-03-31T14:03:17",
      "cpu": 0.0,
      "rss": 29008
    },
    {
      "datetime": "2023-03-31T14:03:18",
      "cpu": 0.1,
      "rss": 29008
    },
    {
      "datetime": "2023-03-31T14:03:19",
      "cpu": 0.0,
      "rss": 29008
    },
    {
      "datetime": "2023-03-31T14:03:20",
      "cpu": 0.1,
      "rss": 29008
    },
    {
      "datetime": "2023-03-31T14:03:21",
      "cpu": 0.0,
      "rss": 29008
    },
    {
      "datetime": "2023-03-31T14:03:24",
      "cpu": 0.0,
      "rss": 29040
    },
    {
      "datetime": "2023-03-31T14:03:30",
      "cpu": 0.1,
      "rss": 29040
    },
    {
      "datetime": "2023-03-31T14:03:31",
      "cpu": 0.0,
      "rss": 29040
    },
    {
      "datetime": "2023-03-31T14:03:38",
      "cpu": 0.1,
      "rss": 29040
    },
    {
      "datetime": "2023-03-31T14:03:39",
      "cpu": 0.0,
      "rss": 29040
    },
    {
      "datetime": "2023-03-31T14:03:42",
      "cpu": 0.1,
      "rss": 29040
    },
    {
      "datetime": "2023-03-31T14:03:43",
      "cpu": 0.0,
      "rss": 29040
    },
    {
      "datetime": "2023-03-31T14:03:44",
      "cpu": 0.1,
      "rss": 29040
    },
    {
      "datetime": "2023-03-31T14:03:45",
      "cpu": 0.0,
      "rss": 29040
    },
    {
      "datetime": "2023-03-31T14:03:54",
      "cpu": 0.3,
      "rss": 29040
    },
    {
      "datetime": "2023-03-31T14:03:55",
      "cpu": 0.0,
      "rss": 29040
    },
    {
      "datetime": "2023-03-31T14:03:56",
      "cpu": 0.1,
      "rss": 29040
    },
    {
      "datetime": "2023-03-31T14:03:57",
      "cpu": 0.0,
      "rss": 29040
    },
    {
      "datetime": "2023-03-31T14:04:06",
      "cpu": 0.3,
      "rss": 29040
    },
    {
      "datetime": "2023-03-31T14:04:07",
      "cpu": 0.0,
      "rss": 29040
    },
    {
      "datetime": "2023-03-31T14:04:08",
      "cpu": 0.1,
      "rss": 29040
    },
    {
      "datetime": "2023-03-31T14:04:09",
      "cpu": 0.0,
      "rss": 29040
    },
    {
      "datetime": "2023-03-31T14:04:20",
      "cpu": 0.1,
      "rss": 29040
    },
    {
      "datetime": "2023-03-31T14:04:21",
      "cpu": 0.0,
      "rss": 29040
    },
    {
      "datetime": "2023-03-31T14:04:32",
      "cpu": 0.1,
      "rss": 29040
    },
    {
      "datetime": "2023-03-31T14:04:33",
      "cpu": 0.0,
      "rss": 29040
    },
    {
      "datetime": "2023-03-31T14:04:34",
      "cpu": 0.2,
      "rss": 29040
    },
    {
      "datetime": "2023-03-31T14:04:35",
      "cpu": 0.0,
      "rss": 29040
    },
    {
      "datetime": "2023-03-31T14:04:44",
      "cpu": 0.4,
      "rss": 28976
    },
    {
      "datetime": "2023-03-31T14:04:45",
      "cpu": 0.0,
      "rss": 28976
    },
    {
      "datetime": "2023-03-31T14:04:46",
      "cpu": 0.1,
      "rss": 28976
    },
    {
      "datetime": "2023-03-31T14:04:47",
      "cpu": 0.0,
      "rss": 28976
    },
    {
      "datetime": "2023-03-31T14:04:48",
      "cpu": 0.1,
      "rss": 28976
    },
    {
      "datetime": "2023-03-31T14:04:49",
      "cpu": 0.0,
      "rss": 28976
    },
    {
      "datetime": "2023-03-31T14:04:58",
      "cpu": 0.4,
      "rss": 28976
    },
    {
      "datetime": "2023-03-31T14:04:59",
      "cpu": 0.0,
      "rss": 28976
    },
    {
      "datetime": "2023-03-31T14:05:00",
      "cpu": 0.1,
      "rss": 28976
    },
    {
      "datetime": "2023-03-31T14:05:01",
      "cpu": 0.0,
      "rss": 28960
    },
    {
      "datetime": "2023-03-31T14:05:02",
      "cpu": 0.1,
      "rss": 28960
    },
    {
      "datetime": "2023-03-31T14:05:03",
      "cpu": 0.0,
      "rss": 28960
    },
    {
      "datetime": "2023-03-31T14:05:12",
      "cpu": 0.4,
      "rss": 28960
    },
    {
      "datetime": "2023-03-31T14:05:13",
      "cpu": 0.0,
      "rss": 28960
    },
    {
      "datetime": "2023-03-31T14:05:17",
      "cpu": 0.0,
      "rss": 28928
    },
    {
      "datetime": "2023-03-31T14:05:26",
      "cpu": 0.1,
      "rss": 28928
    },
    {
      "datetime": "2023-03-31T14:05:27",
      "cpu": 0.0,
      "rss": 28928
    },
    {
      "datetime": "2023-03-31T14:05:33",
      "cpu": 0.0,
      "rss": 29040
    },
    {
      "datetime": "2023-03-31T14:05:34",
      "cpu": 0.0,
      "rss": 29056
    },
    {
      "datetime": "2023-03-31T14:05:39",
      "cpu": 0.0,
      "rss": 29088
    },
    {
      "datetime": "2023-03-31T14:05:42",
      "cpu": 0.2,
      "rss": 29088
    },
    {
      "datetime": "2023-03-31T14:05:43",
      "cpu": 0.0,
      "rss": 29088
    },
    {
      "datetime": "2023-03-31T14:05:46",
      "cpu": 0.1,
      "rss": 29088
    },
    {
      "datetime": "2023-03-31T14:05:47",
      "cpu": 0.0,
      "rss": 29088
    },
    {
      "datetime": "2023-03-31T14:05:54",
      "cpu": 0.0,
      "rss": 29168
    },
    {
      "datetime": "2023-03-31T14:05:58",
      "cpu": 0.4,
      "rss": 29168
    },
    {
      "datetime": "2023-03-31T14:05:59",
      "cpu": 0.0,
      "rss": 29168
    },
    {
      "datetime": "2023-03-31T14:06:02",
      "cpu": 0.1,
      "rss": 29168
    },
    {
      "datetime": "2023-03-31T14:06:03",
      "cpu": 0.0,
      "rss": 29168
    },
    {
      "datetime": "2023-03-31T14:06:14",
      "cpu": 0.2,
      "rss": 29168
    },
    {
      "datetime": "2023-03-31T14:06:15",
      "cpu": 0.0,
      "rss": 29168
    },
    {
      "datetime": "2023-03-31T14:06:16",
      "cpu": 0.1,
      "rss": 29168
    },
    {
      "datetime": "2023-03-31T14:06:17",
      "cpu": 0.0,
      "rss": 29168
    },
    {
      "datetime": "2023-03-31T14:06:28",
      "cpu": 0.1,
      "rss": 29168
    },
    {
      "datetime": "2023-03-31T14:06:29",
      "cpu": 0.0,
      "rss": 29168
    },
    {
      "datetime": "2023-03-31T14:06:33",
      "cpu": 0.1,
      "rss": 29168
    },
    {
      "datetime": "2023-03-31T14:06:35",
      "cpu": 0.0,
      "rss": 29168
    },
    {
      "datetime": "2023-03-31T14:06:40",
      "cpu": 0.1,
      "rss": 29168
    },
    {
      "datetime": "2023-03-31T14:06:41",
      "cpu": 0.0,
      "rss": 29168
    },
    {
      "datetime": "2023-03-31T14:06:52",
      "cpu": 0.6,
      "rss": 29168
    },
    {
      "datetime": "2023-03-31T14:06:53",
      "cpu": 0.0,
      "rss": 29168
    },
    {
      "datetime": "2023-03-31T14:06:54",
      "cpu": 0.1,
      "rss": 29168
    },
    {
      "datetime": "2023-03-31T14:06:55",
      "cpu": 0.0,
      "rss": 29168
    },
    {
      "datetime": "2023-03-31T14:06:56",
      "cpu": 0.1,
      "rss": 29168
    },
    {
      "datetime": "2023-03-31T14:06:57",
      "cpu": 0.0,
      "rss": 29168
    },
    {
      "datetime": "2023-03-31T14:07:04",
      "cpu": 0.3,
      "rss": 29168
    },
    {
      "datetime": "2023-03-31T14:07:05",
      "cpu": 0.0,
      "rss": 29168
    },
    {
      "datetime": "2023-03-31T14:07:06",
      "cpu": 0.2,
      "rss": 29168
    },
    {
      "datetime": "2023-03-31T14:07:07",
      "cpu": 0.0,
      "rss": 29168
    },
    {
      "datetime": "2023-03-31T14:07:17",
      "cpu": 0.0,
      "rss": 29152
    },
    {
      "datetime": "2023-03-31T14:07:18",
      "cpu": 0.1,
      "rss": 28656
    },
    {
      "datetime": "2023-03-31T14:07:19",
      "cpu": 0.0,
      "rss": 28640
    },
    {
      "datetime": "2023-03-31T14:07:20",
      "cpu": 0.0,
      "rss": 27760
    },
    {
      "datetime": "2023-03-31T14:07:22",
      "cpu": 0.0,
      "rss": 18624
    },
    {
      "datetime": "2023-03-31T14:07:23",
      "cpu": 0.0,
      "rss": 18496
    },
    {
      "datetime": "2023-03-31T14:07:24",
      "cpu": 0.0,
      "rss": 18512
    },
    {
      "datetime": "2023-03-31T14:07:27",
      "cpu": 0.0,
      "rss": 18288
    },
    {
      "datetime": "2023-03-31T14:07:29",
      "cpu": 0.0,
      "rss": 18320
    },
    {
      "datetime": "2023-03-31T14:07:32",
      "cpu": 0.1,
      "rss": 18320
    },
    {
      "datetime": "2023-03-31T14:07:33",
      "cpu": 0.0,
      "rss": 18320
    },
    {
      "datetime": "2023-03-31T14:07:34",
      "cpu": 0.0,
      "rss": 18352
    },
    {
      "datetime": "2023-03-31T14:07:39",
      "cpu": 0.1,
      "rss": 18352
    },
    {
      "datetime": "2023-03-31T14:07:40",
      "cpu": 0.0,
      "rss": 18352
    },
    {
      "datetime": "2023-03-31T14:07:44",
      "cpu": 0.2,
      "rss": 18352
    },
    {
      "datetime": "2023-03-31T14:07:45",
      "cpu": 0.0,
      "rss": 18352
    },
    {
      "datetime": "2023-03-31T14:07:56",
      "cpu": 0.2,
      "rss": 18352
    },
    {
      "datetime": "2023-03-31T14:07:57",
      "cpu": 0.0,
      "rss": 18352
    },
    {
      "datetime": "2023-03-31T14:08:04",
      "cpu": 0.1,
      "rss": 18352
    },
    {
      "datetime": "2023-03-31T14:08:05",
      "cpu": 0.0,
      "rss": 18352
    },
    {
      "datetime": "2023-03-31T14:08:08",
      "cpu": 0.1,
      "rss": 18352
    },
    {
      "datetime": "2023-03-31T14:08:09",
      "cpu": 0.0,
      "rss": 18352
    },
    {
      "datetime": "2023-03-31T14:08:10",
      "cpu": 0.1,
      "rss": 18352
    },
    {
      "datetime": "2023-03-31T14:08:11",
      "cpu": 0.0,
      "rss": 18352
    },
    {
      "datetime": "2023-03-31T14:08:14",
      "cpu": 0.0,
      "rss": 18384
    },
    {
      "datetime": "2023-03-31T14:08:21",
      "cpu": 0.0,
      "rss": 18432
    },
    {
      "datetime": "2023-03-31T14:08:24",
      "cpu": 0.2,
      "rss": 18432
    },
    {
      "datetime": "2023-03-31T14:08:25",
      "cpu": 0.0,
      "rss": 18432
    },
    {
      "datetime": "2023-03-31T14:08:26",
      "cpu": 0.1,
      "rss": 18432
    },
    {
      "datetime": "2023-03-31T14:08:27",
      "cpu": 0.0,
      "rss": 18432
    },
    {
      "datetime": "2023-03-31T14:08:38",
      "cpu": 0.4,
      "rss": 18432
    },
    {
      "datetime": "2023-03-31T14:08:39",
      "cpu": 0.0,
      "rss": 18432
    },
    {
      "datetime": "2023-03-31T14:08:42",
      "cpu": 0.1,
      "rss": 18432
    },
    {
      "datetime": "2023-03-31T14:08:43",
      "cpu": 0.0,
      "rss": 18432
    },
    {
      "datetime": "2023-03-31T14:08:46",
      "cpu": 0.0,
      "rss": 22800
    },
    {
      "datetime": "2023-03-31T14:08:47",
      "cpu": 0.0,
      "rss": 22816
    },
    {
      "datetime": "2023-03-31T14:08:50",
      "cpu": 0.2,
      "rss": 22816
    },
    {
      "datetime": "2023-03-31T14:08:51",
      "cpu": 0.0,
      "rss": 22784
    },
    {
      "datetime": "2023-03-31T14:08:52",
      "cpu": 0.1,
      "rss": 22784
    },
    {
      "datetime": "2023-03-31T14:08:53",
      "cpu": 0.0,
      "rss": 22784
    },
    {
      "datetime": "2023-03-31T14:08:54",
      "cpu": 0.1,
      "rss": 22784
    },
    {
      "datetime": "2023-03-31T14:08:55",
      "cpu": 0.0,
      "rss": 22784
    },
    {
      "datetime": "2023-03-31T14:08:56",
      "cpu": 0.1,
      "rss": 22784
    },
    {
      "datetime": "2023-03-31T14:08:57",
      "cpu": 0.0,
      "rss": 22784
    },
    {
      "datetime": "2023-03-31T14:08:59",
      "cpu": 0.1,
      "rss": 22816
    },
    {
      "datetime": "2023-03-31T14:09:00",
      "cpu": 0.0,
      "rss": 22816
    },
    {
      "datetime": "2023-03-31T14:09:02",
      "cpu": 0.0,
      "rss": 22768
    },
    {
      "datetime": "2023-03-31T14:09:04",
      "cpu": 0.1,
      "rss": 22768
    },
    {
      "datetime": "2023-03-31T14:09:05",
      "cpu": 0.0,
      "rss": 22768
    },
    {
      "datetime": "2023-03-31T14:09:06",
      "cpu": 0.1,
      "rss": 22768
    },
    {
      "datetime": "2023-03-31T14:09:07",
      "cpu": 0.0,
      "rss": 22768
    },
    {
      "datetime": "2023-03-31T14:09:08",
      "cpu": 0.1,
      "rss": 22768
    },
    {
      "datetime": "2023-03-31T14:09:09",
      "cpu": 0.0,
      "rss": 22768
    },
    {
      "datetime": "2023-03-31T14:09:17",
      "cpu": 0.5,
      "rss": 22992
    },
    {
      "datetime": "2023-03-31T14:09:18",
      "cpu": 0.0,
      "rss": 22992
    },
    {
      "datetime": "2023-03-31T14:09:20",
      "cpu": 0.1,
      "rss": 22992
    },
    {
      "datetime": "2023-03-31T14:09:21",
      "cpu": 0.0,
      "rss": 22992
    },
    {
      "datetime": "2023-03-31T14:09:22",
      "cpu": 0.1,
      "rss": 22992
    },
    {
      "datetime": "2023-03-31T14:09:23",
      "cpu": 0.0,
      "rss": 22992
    },
    {
      "datetime": "2023-03-31T14:09:29",
      "cpu": 0.1,
      "rss": 22992
    },
    {
      "datetime": "2023-03-31T14:09:30",
      "cpu": 0.0,
      "rss": 22992
    },
    {
      "datetime": "2023-03-31T14:09:31",
      "cpu": 0.0,
      "rss": 22928
    },
    {
      "datetime": "2023-03-31T14:09:32",
      "cpu": 0.0,
      "rss": 22960
    },
    {
      "datetime": "2023-03-31T14:09:34",
      "cpu": 0.3,
      "rss": 22960
    },
    {
      "datetime": "2023-03-31T14:09:35",
      "cpu": 0.0,
      "rss": 22960
    },
    {
      "datetime": "2023-03-31T14:09:38",
      "cpu": 0.1,
      "rss": 22960
    },
    {
      "datetime": "2023-03-31T14:09:40",
      "cpu": 0.0,
      "rss": 22880
    },
    {
      "datetime": "2023-03-31T14:09:41",
      "cpu": 0.0,
      "rss": 22832
    },
    {
      "datetime": "2023-03-31T14:09:46",
      "cpu": 0.1,
      "rss": 22832
    },
    {
      "datetime": "2023-03-31T14:09:47",
      "cpu": 0.0,
      "rss": 22832
    },
    {
      "datetime": "2023-03-31T14:10:00",
      "cpu": 0.2,
      "rss": 22832
    },
    {
      "datetime": "2023-03-31T14:10:01",
      "cpu": 0.0,
      "rss": 22832
    },
    {
      "datetime": "2023-03-31T14:10:04",
      "cpu": 0.0,
      "rss": 22848
    },
    {
      "datetime": "2023-03-31T14:10:14",
      "cpu": 0.3,
      "rss": 22848
    },
    {
      "datetime": "2023-03-31T14:10:15",
      "cpu": 0.0,
      "rss": 22848
    },
    {
      "datetime": "2023-03-31T14:10:16",
      "cpu": 0.1,
      "rss": 22848
    },
    {
      "datetime": "2023-03-31T14:10:17",
      "cpu": 0.0,
      "rss": 22848
    },
    {
      "datetime": "2023-03-31T14:10:18",
      "cpu": 0.2,
      "rss": 22848
    },
    {
      "datetime": "2023-03-31T14:10:20",
      "cpu": 0.0,
      "rss": 22848
    },
    {
      "datetime": "2023-03-31T14:10:25",
      "cpu": 0.0,
      "rss": 22816
    },
    {
      "datetime": "2023-03-31T14:10:28",
      "cpu": 0.3,
      "rss": 22816
    },
    {
      "datetime": "2023-03-31T14:10:29",
      "cpu": 0.0,
      "rss": 22816
    },
    {
      "datetime": "2023-03-31T14:10:30",
      "cpu": 0.1,
      "rss": 22816
    },
    {
      "datetime": "2023-03-31T14:10:31",
      "cpu": 0.0,
      "rss": 22816
    },
    {
      "datetime": "2023-03-31T14:10:37",
      "cpu": 0.0,
      "rss": 22736
    },
    {
      "datetime": "2023-03-31T14:10:39",
      "cpu": 0.0,
      "rss": 22768
    },
    {
      "datetime": "2023-03-31T14:10:40",
      "cpu": 0.4,
      "rss": 22784
    },
    {
      "datetime": "2023-03-31T14:10:41",
      "cpu": 0.0,
      "rss": 22784
    },
    {
      "datetime": "2023-03-31T14:10:42",
      "cpu": 0.3,
      "rss": 22784
    },
    {
      "datetime": "2023-03-31T14:10:43",
      "cpu": 0.0,
      "rss": 22784
    },
    {
      "datetime": "2023-03-31T14:10:44",
      "cpu": 0.1,
      "rss": 22784
    },
    {
      "datetime": "2023-03-31T14:10:46",
      "cpu": 0.0,
      "rss": 22784
    },
    {
      "datetime": "2023-03-31T14:10:52",
      "cpu": 0.0,
      "rss": 22864
    },
    {
      "datetime": "2023-03-31T14:10:55",
      "cpu": 0.0,
      "rss": 18416
    },
    {
      "datetime": "2023-03-31T14:10:56",
      "cpu": 0.0,
      "rss": 18288
    },
    {
      "datetime": "2023-03-31T14:10:59",
      "cpu": 0.1,
      "rss": 18288
    },
    {
      "datetime": "2023-03-31T14:11:00",
      "cpu": 0.0,
      "rss": 18288
    },
    {
      "datetime": "2023-03-31T14:11:06",
      "cpu": 0.2,
      "rss": 18288
    },
    {
      "datetime": "2023-03-31T14:11:07",
      "cpu": 0.0,
      "rss": 18288
    },
    {
      "datetime": "2023-03-31T14:11:08",
      "cpu": 0.1,
      "rss": 18288
    },
    {
      "datetime": "2023-03-31T14:11:09",
      "cpu": 0.0,
      "rss": 18288
    },
    {
      "datetime": "2023-03-31T14:11:17",
      "cpu": 0.0,
      "rss": 18304
    },
    {
      "datetime": "2023-03-31T14:11:20",
      "cpu": 0.1,
      "rss": 18304
    },
    {
      "datetime": "2023-03-31T14:11:21",
      "cpu": 0.0,
      "rss": 18304
    },
    {
      "datetime": "2023-03-31T14:11:22",
      "cpu": 0.1,
      "rss": 18304
    },
    {
      "datetime": "2023-03-31T14:11:23",
      "cpu": 0.0,
      "rss": 18304
    },
    {
      "datetime": "2023-03-31T14:11:25",
      "cpu": 0.0,
      "rss": 18336
    },
    {
      "datetime": "2023-03-31T14:11:34",
      "cpu": 0.3,
      "rss": 18336
    },
    {
      "datetime": "2023-03-31T14:11:35",
      "cpu": 0.0,
      "rss": 18336
    },
    {
      "datetime": "2023-03-31T14:11:36",
      "cpu": 0.1,
      "rss": 18336
    },
    {
      "datetime": "2023-03-31T14:11:37",
      "cpu": 0.0,
      "rss": 18336
    },
    {
      "datetime": "2023-03-31T14:11:48",
      "cpu": 0.3,
      "rss": 18336
    },
    {
      "datetime": "2023-03-31T14:11:49",
      "cpu": 0.0,
      "rss": 18336
    },
    {
      "datetime": "2023-03-31T14:11:58",
      "cpu": 0.1,
      "rss": 20944
    },
    {
      "datetime": "2023-03-31T14:11:59",
      "cpu": 0.0,
      "rss": 20880
    },
    {
      "datetime": "2023-03-31T14:12:01",
      "cpu": 0.0,
      "rss": 20928
    },
    {
      "datetime": "2023-03-31T14:12:02",
      "cpu": 0.2,
      "rss": 20928
    },
    {
      "datetime": "2023-03-31T14:12:03",
      "cpu": 0.0,
      "rss": 20928
    },
    {
      "datetime": "2023-03-31T14:12:07",
      "cpu": 0.1,
      "rss": 20928
    },
    {
      "datetime": "2023-03-31T14:12:08",
      "cpu": 0.0,
      "rss": 20928
    },
    {
      "datetime": "2023-03-31T14:12:09",
      "cpu": 0.1,
      "rss": 20928
    },
    {
      "datetime": "2023-03-31T14:12:10",
      "cpu": 0.0,
      "rss": 20928
    },
    {
      "datetime": "2023-03-31T14:12:16",
      "cpu": 0.6,
      "rss": 20928
    },
    {
      "datetime": "2023-03-31T14:12:17",
      "cpu": 0.0,
      "rss": 20928
    },
    {
      "datetime": "2023-03-31T14:12:18",
      "cpu": 0.1,
      "rss": 20928
    },
    {
      "datetime": "2023-03-31T14:12:20",
      "cpu": 0.0,
      "rss": 20928
    },
    {
      "datetime": "2023-03-31T14:12:24",
      "cpu": 0.0,
      "rss": 20896
    },
    {
      "datetime": "2023-03-31T14:12:28",
      "cpu": 0.3,
      "rss": 20896
    },
    {
      "datetime": "2023-03-31T14:12:29",
      "cpu": 0.0,
      "rss": 20896
    },
    {
      "datetime": "2023-03-31T14:12:30",
      "cpu": 0.1,
      "rss": 21088
    },
    {
      "datetime": "2023-03-31T14:12:31",
      "cpu": 0.0,
      "rss": 21088
    },
    {
      "datetime": "2023-03-31T14:12:44",
      "cpu": 0.2,
      "rss": 21088
    },
    {
      "datetime": "2023-03-31T14:12:45",
      "cpu": 0.0,
      "rss": 21088
    },
    {
      "datetime": "2023-03-31T14:12:46",
      "cpu": 0.1,
      "rss": 21088
    },
    {
      "datetime": "2023-03-31T14:12:48",
      "cpu": 0.0,
      "rss": 21088
    },
    {
      "datetime": "2023-03-31T14:12:49",
      "cpu": 0.1,
      "rss": 21088
    },
    {
      "datetime": "2023-03-31T14:12:50",
      "cpu": 0.0,
      "rss": 21088
    },
    {
      "datetime": "2023-03-31T14:12:51",
      "cpu": 0.0,
      "rss": 21120
    },
    {
      "datetime": "2023-03-31T14:12:58",
      "cpu": 0.1,
      "rss": 21120
    },
    {
      "datetime": "2023-03-31T14:12:59",
      "cpu": 0.0,
      "rss": 21120
    },
    {
      "datetime": "2023-03-31T14:13:00",
      "cpu": 0.1,
      "rss": 21120
    },
    {
      "datetime": "2023-03-31T14:13:01",
      "cpu": 0.0,
      "rss": 21120
    },
    {
      "datetime": "2023-03-31T14:13:14",
      "cpu": 0.1,
      "rss": 21120
    },
    {
      "datetime": "2023-03-31T14:13:15",
      "cpu": 0.0,
      "rss": 21120
    },
    {
      "datetime": "2023-03-31T14:13:16",
      "cpu": 0.1,
      "rss": 21120
    },
    {
      "datetime": "2023-03-31T14:13:18",
      "cpu": 0.0,
      "rss": 21120
    },
    {
      "datetime": "2023-03-31T14:13:30",
      "cpu": 0.2,
      "rss": 21120
    },
    {
      "datetime": "2023-03-31T14:13:31",
      "cpu": 0.0,
      "rss": 21120
    },
    {
      "datetime": "2023-03-31T14:13:32",
      "cpu": 0.1,
      "rss": 21120
    },
    {
      "datetime": "2023-03-31T14:13:34",
      "cpu": 0.0,
      "rss": 21120
    },
    {
      "datetime": "2023-03-31T14:13:46",
      "cpu": 0.2,
      "rss": 21120
    },
    {
      "datetime": "2023-03-31T14:13:47",
      "cpu": 0.0,
      "rss": 21120
    },
    {
      "datetime": "2023-03-31T14:13:49",
      "cpu": 0.1,
      "rss": 21120
    },
    {
      "datetime": "2023-03-31T14:13:50",
      "cpu": 0.0,
      "rss": 21120
    },
    {
      "datetime": "2023-03-31T14:14:02",
      "cpu": 0.1,
      "rss": 21104
    },
    {
      "datetime": "2023-03-31T14:14:04",
      "cpu": 0.0,
      "rss": 21104
    },
    {
      "datetime": "2023-03-31T14:14:07",
      "cpu": 0.0,
      "rss": 21072
    },
    {
      "datetime": "2023-03-31T14:14:16",
      "cpu": 0.1,
      "rss": 21072
    },
    {
      "datetime": "2023-03-31T14:14:17",
      "cpu": 0.0,
      "rss": 21072
    },
    {
      "datetime": "2023-03-31T14:14:24",
      "cpu": 0.0,
      "rss": 21088
    },
    {
      "datetime": "2023-03-31T14:14:32",
      "cpu": 0.2,
      "rss": 21088
    },
    {
      "datetime": "2023-03-31T14:14:33",
      "cpu": 0.0,
      "rss": 21088
    },
    {
      "datetime": "2023-03-31T14:14:35",
      "cpu": 0.3,
      "rss": 21088
    },
    {
      "datetime": "2023-03-31T14:14:36",
      "cpu": 0.0,
      "rss": 21088
    },
    {
      "datetime": "2023-03-31T14:14:37",
      "cpu": 0.1,
      "rss": 21088
    },
    {
      "datetime": "2023-03-31T14:14:38",
      "cpu": 0.0,
      "rss": 21088
    },
    {
      "datetime": "2023-03-31T14:14:39",
      "cpu": 0.1,
      "rss": 21088
    },
    {
      "datetime": "2023-03-31T14:14:40",
      "cpu": 0.0,
      "rss": 21088
    },
    {
      "datetime": "2023-03-31T14:14:41",
      "cpu": 0.1,
      "rss": 21088
    },
    {
      "datetime": "2023-03-31T14:14:42",
      "cpu": 0.0,
      "rss": 21088
    },
    {
      "datetime": "2023-03-31T14:14:50",
      "cpu": 0.1,
      "rss": 21088
    },
    {
      "datetime": "2023-03-31T14:14:51",
      "cpu": 0.0,
      "rss": 21088
    },
    {
      "datetime": "2023-03-31T14:14:53",
      "cpu": 0.2,
      "rss": 21072
    },
    {
      "datetime": "2023-03-31T14:14:54",
      "cpu": 0.1,
      "rss": 21072
    },
    {
      "datetime": "2023-03-31T14:14:56",
      "cpu": 0.0,
      "rss": 21072
    },
    {
      "datetime": "2023-03-31T14:14:58",
      "cpu": 0.0,
      "rss": 20976
    },
    {
      "datetime": "2023-03-31T14:14:59",
      "cpu": 0.1,
      "rss": 23248
    },
    {
      "datetime": "2023-03-31T14:15:00",
      "cpu": 0.0,
      "rss": 23248
    },
    {
      "datetime": "2023-03-31T14:15:01",
      "cpu": 0.0,
      "rss": 23264
    },
    {
      "datetime": "2023-03-31T14:15:04",
      "cpu": 0.5,
      "rss": 23264
    },
    {
      "datetime": "2023-03-31T14:15:05",
      "cpu": 0.0,
      "rss": 23264
    },
    {
      "datetime": "2023-03-31T14:15:07",
      "cpu": 0.2,
      "rss": 23264
    },
    {
      "datetime": "2023-03-31T14:15:08",
      "cpu": 0.0,
      "rss": 23264
    },
    {
      "datetime": "2023-03-31T14:15:20",
      "cpu": 0.2,
      "rss": 23296
    },
    {
      "datetime": "2023-03-31T14:15:22",
      "cpu": 0.0,
      "rss": 23296
    },
    {
      "datetime": "2023-03-31T14:15:23",
      "cpu": 0.2,
      "rss": 23296
    },
    {
      "datetime": "2023-03-31T14:15:24",
      "cpu": 0.0,
      "rss": 23296
    },
    {
      "datetime": "2023-03-31T14:15:25",
      "cpu": 0.1,
      "rss": 23296
    },
    {
      "datetime": "2023-03-31T14:15:26",
      "cpu": 0.0,
      "rss": 23296
    },
    {
      "datetime": "2023-03-31T14:15:36",
      "cpu": 0.6,
      "rss": 23296
    },
    {
      "datetime": "2023-03-31T14:15:38",
      "cpu": 0.0,
      "rss": 23296
    },
    {
      "datetime": "2023-03-31T14:15:39",
      "cpu": 0.3,
      "rss": 23296
    },
    {
      "datetime": "2023-03-31T14:15:40",
      "cpu": 0.0,
      "rss": 23296
    },
    {
      "datetime": "2023-03-31T14:15:47",
      "cpu": 0.0,
      "rss": 23376
    },
    {
      "datetime": "2023-03-31T14:15:52",
      "cpu": 0.4,
      "rss": 23376
    },
    {
      "datetime": "2023-03-31T14:15:54",
      "cpu": 0.0,
      "rss": 23376
    },
    {
      "datetime": "2023-03-31T14:15:55",
      "cpu": 0.1,
      "rss": 23376
    },
    {
      "datetime": "2023-03-31T14:15:56",
      "cpu": 0.0,
      "rss": 23376
    }
  ],
  "77467": [
    {
      "datetime": "2023-03-31T13:59:16",
      "cpu": 0.0,
      "rss": 19120
    },
    {
      "datetime": "2023-03-31T13:59:21",
      "cpu": 0.3,
      "rss": 29136
    },
    {
      "datetime": "2023-03-31T13:59:22",
      "cpu": 0.0,
      "rss": 29136
    },
    {
      "datetime": "2023-03-31T13:59:38",
      "cpu": 0.0,
      "rss": 25600
    },
    {
      "datetime": "2023-03-31T13:59:39",
      "cpu": 0.0,
      "rss": 18336
    },
    {
      "datetime": "2023-03-31T14:00:57",
      "cpu": 0.0,
      "rss": 18192
    },
    {
      "datetime": "2023-03-31T14:02:43",
      "cpu": 0.7,
      "rss": 33056
    },
    {
      "datetime": "2023-03-31T14:02:44",
      "cpu": 0.0,
      "rss": 33056
    },
    {
      "datetime": "2023-03-31T14:02:51",
      "cpu": 0.0,
      "rss": 32032
    },
    {
      "datetime": "2023-03-31T14:02:52",
      "cpu": 0.0,
      "rss": 31680
    },
    {
      "datetime": "2023-03-31T14:02:55",
      "cpu": 0.0,
      "rss": 30768
    },
    {
      "datetime": "2023-03-31T14:02:56",
      "cpu": 0.0,
      "rss": 30304
    },
    {
      "datetime": "2023-03-31T14:03:15",
      "cpu": 0.0,
      "rss": 28000
    },
    {
      "datetime": "2023-03-31T14:04:44",
      "cpu": 0.0,
      "rss": 24496
    },
    {
      "datetime": "2023-03-31T14:05:33",
      "cpu": 0.0,
      "rss": 24480
    },
    {
      "datetime": "2023-03-31T14:05:54",
      "cpu": 0.0,
      "rss": 29520
    },
    {
      "datetime": "2023-03-31T14:07:17",
      "cpu": 0.0,
      "rss": 29120
    },
    {
      "datetime": "2023-03-31T14:07:18",
      "cpu": 0.0,
      "rss": 28992
    },
    {
      "datetime": "2023-03-31T14:07:20",
      "cpu": 0.0,
      "rss": 19808
    },
    {
      "datetime": "2023-03-31T14:07:22",
      "cpu": 0.0,
      "rss": 8752
    },
    {
      "datetime": "2023-03-31T14:07:27",
      "cpu": 0.0,
      "rss": 8512
    },
    {
      "datetime": "2023-03-31T14:09:02",
      "cpu": 0.0,
      "rss": 3792
    },
    {
      "datetime": "2023-03-31T14:09:17",
      "cpu": 3.7,
      "rss": 26608
    },
    {
      "datetime": "2023-03-31T14:09:18",
      "cpu": 0.0,
      "rss": 26608
    },
    {
      "datetime": "2023-03-31T14:09:40",
      "cpu": 0.0,
      "rss": 26464
    },
    {
      "datetime": "2023-03-31T14:09:41",
      "cpu": 0.0,
      "rss": 26096
    },
    {
      "datetime": "2023-03-31T14:10:55",
      "cpu": 0.0,
      "rss": 24752
    },
    {
      "datetime": "2023-03-31T14:10:56",
      "cpu": 0.0,
      "rss": 24736
    },
    {
      "datetime": "2023-03-31T14:11:58",
      "cpu": 0.0,
      "rss": 11328
    },
    {
      "datetime": "2023-03-31T14:11:59",
      "cpu": 0.0,
      "rss": 5376
    },
    {
      "datetime": "2023-03-31T14:12:24",
      "cpu": 0.0,
      "rss": 3776
    },
    {
      "datetime": "2023-03-31T14:12:30",
      "cpu": 0.6,
      "rss": 27696
    },
    {
      "datetime": "2023-03-31T14:12:31",
      "cpu": 0.0,
      "rss": 27696
    },
    {
      "datetime": "2023-03-31T14:14:05",
      "cpu": 0.0,
      "rss": 27520
    },
    {
      "datetime": "2023-03-31T14:14:06",
      "cpu": 0.0,
      "rss": 27376
    },
    {
      "datetime": "2023-03-31T14:14:07",
      "cpu": 0.0,
      "rss": 27280
    },
    {
      "datetime": "2023-03-31T14:15:47",
      "cpu": 1.3,
      "rss": 31408
    },
    {
      "datetime": "2023-03-31T14:15:48",
      "cpu": 0.0,
      "rss": 31408
    },
    {
      "datetime": "2023-03-31T14:15:56",
      "cpu": 0.0,
      "rss": 31408
    }
  ],
  "77468": [
    {
      "datetime": "2023-03-31T13:59:16",
      "cpu": 0.0,
      "rss": 17552
    },
    {
      "datetime": "2023-03-31T13:59:21",
      "cpu": 0.3,
      "rss": 28080
    },
    {
      "datetime": "2023-03-31T13:59:22",
      "cpu": 0.0,
      "rss": 28080
    },
    {
      "datetime": "2023-03-31T13:59:38",
      "cpu": 0.0,
      "rss": 26224
    },
    {
      "datetime": "2023-03-31T13:59:39",
      "cpu": 0.0,
      "rss": 18912
    },
    {
      "datetime": "2023-03-31T14:00:57",
      "cpu": 0.0,
      "rss": 18832
    },
    {
      "datetime": "2023-03-31T14:02:27",
      "cpu": 1.0,
      "rss": 32208
    },
    {
      "datetime": "2023-03-31T14:02:28",
      "cpu": 0.0,
      "rss": 32208
    },
    {
      "datetime": "2023-03-31T14:02:51",
      "cpu": 0.0,
      "rss": 31776
    },
    {
      "datetime": "2023-03-31T14:02:52",
      "cpu": 0.0,
      "rss": 31664
    },
    {
      "datetime": "2023-03-31T14:02:55",
      "cpu": 0.0,
      "rss": 31056
    },
    {
      "datetime": "2023-03-31T14:02:56",
      "cpu": 0.0,
      "rss": 28944
    },
    {
      "datetime": "2023-03-31T14:03:05",
      "cpu": 0.0,
      "rss": 28928
    },
    {
      "datetime": "2023-03-31T14:03:15",
      "cpu": 0.0,
      "rss": 23568
    },
    {
      "datetime": "2023-03-31T14:05:33",
      "cpu": 0.1,
      "rss": 29024
    },
    {
      "datetime": "2023-03-31T14:05:34",
      "cpu": 0.0,
      "rss": 29024
    },
    {
      "datetime": "2023-03-31T14:07:17",
      "cpu": 0.0,
      "rss": 28736
    },
    {
      "datetime": "2023-03-31T14:07:18",
      "cpu": 0.0,
      "rss": 22224
    },
    {
      "datetime": "2023-03-31T14:07:19",
      "cpu": 0.0,
      "rss": 21792
    },
    {
      "datetime": "2023-03-31T14:07:20",
      "cpu": 0.0,
      "rss": 20992
    },
    {
      "datetime": "2023-03-31T14:07:22",
      "cpu": 0.0,
      "rss": 9216
    },
    {
      "datetime": "2023-03-31T14:08:46",
      "cpu": 0.1,
      "rss": 26544
    },
    {
      "datetime": "2023-03-31T14:08:47",
      "cpu": 0.0,
      "rss": 26544
    },
    {
      "datetime": "2023-03-31T14:09:06",
      "cpu": 0.0,
      "rss": 26304
    },
    {
      "datetime": "2023-03-31T14:09:24",
      "cpu": 0.0,
      "rss": 26288
    },
    {
      "datetime": "2023-03-31T14:09:36",
      "cpu": 0.0,
      "rss": 26272
    },
    {
      "datetime": "2023-03-31T14:10:55",
      "cpu": 0.0,
      "rss": 8736
    },
    {
      "datetime": "2023-03-31T14:10:56",
      "cpu": 0.0,
      "rss": 3904
    },
    {
      "datetime": "2023-03-31T14:11:58",
      "cpu": 1.4,
      "rss": 26384
    },
    {
      "datetime": "2023-03-31T14:11:59",
      "cpu": 0.0,
      "rss": 26384
    },
    {
      "datetime": "2023-03-31T14:14:02",
      "cpu": 0.0,
      "rss": 26048
    },
    {
      "datetime": "2023-03-31T14:14:59",
      "cpu": 1.6,
      "rss": 32480
    },
    {
      "datetime": "2023-03-31T14:15:00",
      "cpu": 0.0,
      "rss": 32480
    },
    {
      "datetime": "2023-03-31T14:15:47",
      "cpu": 0.2,
      "rss": 32528
    },
    {
      "datetime": "2023-03-31T14:15:48",
      "cpu": 0.0,
      "rss": 32528
    },
    {
      "datetime": "2023-03-31T14:15:56",
      "cpu": 0.0,
      "rss": 32528
    }
  ]
}